wemdata/__init__.py
wemdata/wemdatafunctions.py
wemdata-1.0.18.dist-info/LICENSE.md
wemdata-1.0.18.dist-info/METADATA
wemdata-1.0.18.dist-info/WHEEL
wemdata-1.0.18.dist-info/top_level.txt
wemdata-1.0.18.dist-info/RECORD
