Metadata-Version: 2.1
Name: wemdata
Version: 1.0.18
Summary: Package for extracting data from the Wholesale Electricity Market (WEM) of Western Australia and store in dataframe
Home-page: https://github.com/igchin/WEMProject
Author: Ignatius Chin
Author-email: ignatius.chin@gmail.com
License: UNKNOWN
Platform: UNKNOWN
Classifier: Programming Language :: Python :: 3
Classifier: License :: OSI Approved :: MIT License
Classifier: Operating System :: OS Independent
Requires-Python: >=3.6
